spider_fingerprint_py-0.0.20.dist-info/METADATA
spider_fingerprint_py-0.0.20.dist-info/WHEEL
spider_fingerprint_py-0.0.20.dist-info/licenses/LICENSE.txt
spider_fingerprint_py/__init__.py
spider_fingerprint_py/spider_fingerprint_py.cpython-37m-powerpc64le-linux-gnu.so
spider_fingerprint_py-0.0.20.dist-info/RECORD
