Metadata-Version: 2.4
Name: spider_fingerprint_py
Version: 0.0.20
Classifier: Programming Language :: Rust
Classifier: Programming Language :: Python :: Implementation :: CPython
Classifier: Programming Language :: Python :: Implementation :: PyPy
License-File: LICENSE.txt
Summary: The spider_fingerprint project for python.
License: MIT
Requires-Python: >=3.7
Project-URL: Source Code, https://github.com/tzafon/spider_fingerprint_py
